Workbook

Sheet Scenarios
A1: PADEL FINANCIAL MODEL — Target: €10,000 NET profit / month
A2: ALL NUMBERS ARE ASSUMPTIONS TO VALIDATE. Edit the yellow INPUT cells; green OUTPUT cells recalculate automatically.
B4: Conservative | C4: Realistic | D4: Optimistic | E4: Notes / formula
A5: — INPUTS (edit these) —
A6: Average Order Value, AOV (€) | B6: 60 | C6: 70 | D6: 82 | E6: Blended cart: consumables + accessories + bundles
A7: COGS (% of revenue) | B7: 0.42 | C7: 0.38 | D7: 0.36 | E7: Product + inbound shipping. Lower = more private-label
A8: Return / refund rate (%) | B8: 0.07 | C8: 0.05 | D8: 0.04 | E8: Padel gear returns are modest; validate
A9: Return loss factor (% of returned value) | B9: 0.6 | C9: 0.6 | D9: 0.6 | E9: Share of a returned order's value you lose (ship+restock)
A10: Payment fee (% of revenue) | B10: 0.025 | C10: 0.025 | D10: 0.025 | E10: Stripe/Shopify Payments ~2.5% (EU cards)
A11: Payment fee (fixed €/order) | B11: 0.3 | C11: 0.3 | D11: 0.3 | E11: Per-transaction fixed component
A12: CPM — cost / 1000 impressions (€) | B12: 16 | C12: 15 | D12: 14 | E12: Meta EU, engaged niche. VALIDATE in your accounts
A13: CTR — click-through rate (%) | B13: 0.016 | C13: 0.017 | D13: 0.017 | E13: Strong creative in a passionate niche
A14: CVR — landing→purchase (%) | B14: 0.03 | C14: 0.024 | D14: 0.021 | E14: Cold traffic. Bundles can lift this
A15: Returning revenue share (% of revenue) | B15: 0.28 | C15: 0.33 | D15: 0.35 | E15: Repeat orders carry NO ad cost — your Klaviyo edge
A16: Fixed monthly costs (€) | B16: 350 | C16: 350 | D16: 350 | E16: Shopify+apps+Klaviyo+domain (rises with scale)
A17: Target monthly NET profit (€) | B17: 10000 | C17: 10000 | D17: 10000 | E17: Your goal
A19: — DERIVED UNIT ECONOMICS —
A20: CPC — cost per click (€) | B20: =B12/1000/B13 | C20: =C12/1000/C13 | D20: =D12/1000/D13 | E20: =CPM / 1000 / CTR
A21: CAC — cost per NEW customer (€) | B21: =B20/B14 | C21: =C20/C14 | D21: =D20/D14 | E21: =CPC / CVR
A22: First-order ROAS (AOV / CAC) | B22: =B6/B21 | C22: =C6/C21 | D22: =D6/D21 | E22: Revenue per €1 ad, first order only
A23: Gross contribution margin (cm0) | B23: =1-B7-B10-B8*B9 | C23: =1-C7-C10-C8*C9 | D23: =1-D7-D10-D8*D9 | E23: Margin before ad spend & fixed costs
A24: First-order BREAK-EVEN ROAS | B24: =1/B23 | C24: =1/C23 | D24: =1/D23 | E24: Below this you LOSE on first order (rely on repeat)
A25: Ad spend (% of revenue / MER) | B25: =(1-B15)/B22 | C25: =(1-C15)/C22 | D25: =(1-D15)/D22 | E25: =(1 - returning share) / first-order ROAS
A26: Blended ROAS (Revenue / Ad spend) | B26: =B22/(1-B15) | C26: =C22/(1-C15) | D26: =D22/(1-D15) | E26: Lifted above first-order ROAS by repeat revenue
A28: — WHAT IT TAKES TO HIT €10k NET / MONTH —
A29: Net margin % (before fixed) | B29: =B23-B11/B6-B25 | C29: =C23-C11/C6-C25 | D29: =D23-D11/D6-D25 | E29: =cm0 - per-order fixed fee - ad%
A30: Revenue needed (€/month) | B30: =(B17+B16)/B29 | C30: =(C17+C16)/C29 | D30: =(D17+D16)/D29 | E30: Revenue required so NET = target
A31: Net margin % (actual) | B31: =B17/B30 | C31: =C17/C30 | D31: =D17/D30 | E31: =Target / Revenue
A32: Orders / month | B32: =B30/B6 | C32: =C30/C6 | D32: =D30/D6 | E32: =Revenue / AOV
A33: Orders / day | B33: =B32/30 | C33: =C32/30 | D33: =D32/30 | E33: =Orders / 30
A34: Ad spend / month (€) | B34: =B30*B25 | C34: =C30*C25 | D34: =D30*D25 | E34: Working capital you must fund
A35: New customers / month | B35: =B34/B21 | C35: =C34/C21 | D35: =D34/D21 | E35: =Ad spend / CAC
A36: Returning revenue / month (€) | B36: =B30*B15 | C36: =C30*C15 | D36: =D30*D15 | E36: No ad cost — pure retention value
A37: Gross profit / month (€) | B37: =B30*B23-B32*B11 | C37: =C30*C23-C32*C11 | D37: =D30*D23-D32*D11 | E37: Before ad spend & fixed
A38: NET profit check (€) | B38: =B37-B34-B16 | C38: =C37-C34-C16 | D38: =D37-D34-D16 | E38: Should ≈ target (€10,000)
A40: Reading it: Conservative needs the most revenue/orders because thin margins + weaker retention force huge volume.
A41: Notice (Conservative): First-order ROAS < Break-even ROAS → you lose on acquisition and survive ONLY on repeat purchases.

Sheet Realistic 12-Mo Ramp
A1: REALISTIC SCENARIO — 12-MONTH RAMP (illustrative, editable)
A2: Months 1-2 = ad testing (loss-making by design). Edit the yellow Ad-spend & CAC-multiplier cells. Other columns pull unit economics from the 'Scenarios' sheet (Realistic column C).
A4: Monthly reorder rate (of prior customer base) | B4: 0.07 | C4: ≈ what % of all prior customers buy again each month (drives returning revenue)
A6: Month | B6: Ad spend € (input) | C6: CAC mult (input) | D6: New custs | E6: Cumul. custs | F6: New rev € | G6: Returning rev € | H6: Total rev € | I6: Gross profit € | J6: Fixed € | K6: NET profit € | L6: Cumulative NET €
A7: 1 | B7: 800 | C7: 1.6 | D7: =B7/(Scenarios!$C$21*C7) | E7: =D7 | F7: =D7*Scenarios!$C$6 | G7: 0 | H7: =F7+G7 | I7: =H7*Scenarios!$C$23-(H7/Scenarios!$C$6)*Scenarios!$C$11 | J7: =Scenarios!$C$16 | K7: =I7-B7-J7 | L7: =K7
A8: 2 | B8: 800 | C8: 1.5 | D8: =B8/(Scenarios!$C$21*C8) | E8: =E7+D8 | F8: =D8*Scenarios!$C$6 | G8: =E7*$B$4*Scenarios!$C$6 | H8: =F8+G8 | I8: =H8*Scenarios!$C$23-(H8/Scenarios!$C$6)*Scenarios!$C$11 | J8: =Scenarios!$C$16 | K8: =I8-B8-J8 | L8: =L7+K8
A9: 3 | B9: 1500 | C9: 1.4 | D9: =B9/(Scenarios!$C$21*C9) | E9: =E8+D9 | F9: =D9*Scenarios!$C$6 | G9: =E8*$B$4*Scenarios!$C$6 | H9: =F9+G9 | I9: =H9*Scenarios!$C$23-(H9/Scenarios!$C$6)*Scenarios!$C$11 | J9: =Scenarios!$C$16 | K9: =I9-B9-J9 | L9: =L8+K9
A10: 4 | B10: 3000 | C10: 1.3 | D10: =B10/(Scenarios!$C$21*C10) | E10: =E9+D10 | F10: =D10*Scenarios!$C$6 | G10: =E9*$B$4*Scenarios!$C$6 | H10: =F10+G10 | I10: =H10*Scenarios!$C$23-(H10/Scenarios!$C$6)*Scenarios!$C$11 | J10: =Scenarios!$C$16 | K10: =I10-B10-J10 | L10: =L9+K10
A11: 5 | B11: 6000 | C11: 1.2 | D11: =B11/(Scenarios!$C$21*C11) | E11: =E10+D11 | F11: =D11*Scenarios!$C$6 | G11: =E10*$B$4*Scenarios!$C$6 | H11: =F11+G11 | I11: =H11*Scenarios!$C$23-(H11/Scenarios!$C$6)*Scenarios!$C$11 | J11: =Scenarios!$C$16 | K11: =I11-B11-J11 | L11: =L10+K11
A12: 6 | B12: 9000 | C12: 1.15 | D12: =B12/(Scenarios!$C$21*C12) | E12: =E11+D12 | F12: =D12*Scenarios!$C$6 | G12: =E11*$B$4*Scenarios!$C$6 | H12: =F12+G12 | I12: =H12*Scenarios!$C$23-(H12/Scenarios!$C$6)*Scenarios!$C$11 | J12: =Scenarios!$C$16 | K12: =I12-B12-J12 | L12: =L11+K12
A13: 7 | B13: 12000 | C13: 1.1 | D13: =B13/(Scenarios!$C$21*C13) | E13: =E12+D13 | F13: =D13*Scenarios!$C$6 | G13: =E12*$B$4*Scenarios!$C$6 | H13: =F13+G13 | I13: =H13*Scenarios!$C$23-(H13/Scenarios!$C$6)*Scenarios!$C$11 | J13: =Scenarios!$C$16 | K13: =I13-B13-J13 | L13: =L12+K13
A14: 8 | B14: 15000 | C14: 1.05 | D14: =B14/(Scenarios!$C$21*C14) | E14: =E13+D14 | F14: =D14*Scenarios!$C$6 | G14: =E13*$B$4*Scenarios!$C$6 | H14: =F14+G14 | I14: =H14*Scenarios!$C$23-(H14/Scenarios!$C$6)*Scenarios!$C$11 | J14: =Scenarios!$C$16 | K14: =I14-B14-J14 | L14: =L13+K14
A15: 9 | B15: 17000 | C15: 1 | D15: =B15/(Scenarios!$C$21*C15) | E15: =E14+D15 | F15: =D15*Scenarios!$C$6 | G15: =E14*$B$4*Scenarios!$C$6 | H15: =F15+G15 | I15: =H15*Scenarios!$C$23-(H15/Scenarios!$C$6)*Scenarios!$C$11 | J15: =Scenarios!$C$16 | K15: =I15-B15-J15 | L15: =L14+K15
A16: 10 | B16: 18500 | C16: 1 | D16: =B16/(Scenarios!$C$21*C16) | E16: =E15+D16 | F16: =D16*Scenarios!$C$6 | G16: =E15*$B$4*Scenarios!$C$6 | H16: =F16+G16 | I16: =H16*Scenarios!$C$23-(H16/Scenarios!$C$6)*Scenarios!$C$11 | J16: =Scenarios!$C$16 | K16: =I16-B16-J16 | L16: =L15+K16
A17: 11 | B17: 19500 | C17: 1 | D17: =B17/(Scenarios!$C$21*C17) | E17: =E16+D17 | F17: =D17*Scenarios!$C$6 | G17: =E16*$B$4*Scenarios!$C$6 | H17: =F17+G17 | I17: =H17*Scenarios!$C$23-(H17/Scenarios!$C$6)*Scenarios!$C$11 | J17: =Scenarios!$C$16 | K17: =I17-B17-J17 | L17: =L16+K17
A18: 12 | B18: 20000 | C18: 1 | D18: =B18/(Scenarios!$C$21*C18) | E18: =E17+D18 | F18: =D18*Scenarios!$C$6 | G18: =E17*$B$4*Scenarios!$C$6 | H18: =F18+G18 | I18: =H18*Scenarios!$C$23-(H18/Scenarios!$C$6)*Scenarios!$C$11 | J18: =Scenarios!$C$16 | K18: =I18-B18-J18 | L18: =L17+K18
A20: Illustrative ramp: early months are negative on purpose (validation). NET turns positive once retention + scale compound. Tune ad-spend to your real cash runway.

Sheet Assumptions & Notes
A1: PADEL FINANCIAL MODEL — READ ME
A3: Every figure here is an ASSUMPTION you must validate with your own data. Treat outputs as a
A4: planning compass, not a promise. There is no guaranteed winning product.
A6: HOW THE MODEL WORKS
A7: • Yellow cells = inputs you edit. Green/blue cells = formulas that recalc automatically.
A8: • CAC is derived from your funnel: CPC = CPM/1000/CTR, then CAC = CPC/CVR.
A9: • 'Returning revenue share' is the % of monthly revenue from repeat customers — it carries NO
A10: ad cost, so it directly lifts blended ROAS and net margin. This is where Klaviyo retention pays off.
A11: • Revenue-needed is solved so NET profit = your €10k target for each scenario.
A13: KEY BENCHMARKS TO VALIDATE (sources: 2026 market research — see business-plan.md)
A14: • AOV €60–82: blended cart of consumables (balls, grips), accessories (bags, dampeners) and bundles.
A15: • COGS 36–42%: depends on resale (branded balls/rackets, lower margin) vs private-label (grips/bags, higher).
... A25: 3. Scaling ad spend ties up real cash. Fund the ramp from the working-capital line, not from hoped-for profit.
